hydrazine/src/postgres.py
hydrazine-0.0.1.dist-info/LICENSE
hydrazine-0.0.1.dist-info/METADATA
hydrazine-0.0.1.dist-info/WHEEL
hydrazine-0.0.1.dist-info/top_level.txt
hydrazine-0.0.1.dist-info/RECORD
