Metadata-Version: 2.1
Name: hydrazine
Version: 0.0.1
Summary: Filesystem handling utilities
Author-email: "Julian M. Kleber" <julian.m.kleber@gmail.com>
Project-URL: Homepage, https://www.codeberg.org/cap_jmk/amarium.git
Project-URL: Bug Tracker, https://www.codeberg.org/cap_jmk/amarium.git/issues
Classifier: Programming Language :: Python :: 3
Classifier: License :: OSI Approved :: GNU General Public License v3 (GPLv3)
Classifier: Operating System :: OS Independent
Requires-Python: >=3.8
License-File: LICENSE
Requires-Dist: pandas
Requires-Dist: psycopg2-binary
Requires-Dist: sqlalchemy
